grippy/__init__.py
grippy/app.py
grippy/import_helpers.py
grippy/parse.py
grippy/proto_message.py
grippy/types.py
grippy-0.0.2.dist-info/WHEEL
grippy-0.0.2.dist-info/METADATA
grippy-0.0.2.dist-info/RECORD
